processing/__init__.py
processing/combinantion.py
processing/tranformation.py
utils/__init__.py
utils/io.py
utils/plot.py
gustavo_pacote_processamento_imagens-0.0.1.dist-info/METADATA
gustavo_pacote_processamento_imagens-0.0.1.dist-info/WHEEL
gustavo_pacote_processamento_imagens-0.0.1.dist-info/top_level.txt
gustavo_pacote_processamento_imagens-0.0.1.dist-info/RECORD
