Metadata-Version: 2.1
Name: gustavo-pacote-processamento-imagens
Version: 0.0.1
Summary: My short description
Home-page: https://github.com/Gustavo-Lima17/pacote-processamento-imagens
Author: Gustavo_lima
Author-email: gustavofifa580@gmail.com
License: UNKNOWN
Platform: UNKNOWN
Requires-Python: >=3.8
